file_reader/__init__.py
file_reader/__main__.py
file_reader/multireader.py
file_reader/compressed/__init__.py
file_reader/compressed/bzipped.py
file_reader/compressed/gzipped.py
file_reader/util/__init__.py
file_reader/util/writer.py
file_reader_demo-1.0.0.dist-info/METADATA
file_reader_demo-1.0.0.dist-info/WHEEL
file_reader_demo-1.0.0.dist-info/top_level.txt
file_reader_demo-1.0.0.dist-info/RECORD
