Metadata-Version: 2.1
Name: file-reader-demo
Version: 1.0.0
Summary: Tools for reading various file formats
Home-page: UNKNOWN
Author: UNKNOWN
Author-email: UNKNOWN
License: UNKNOWN
Platform: UNKNOWN
